cjy_wfy4/__init__.py
cjy_wfy4/background.jpg
cjy_wfy4/crash.wav
cjy_wfy4/main.py
cjy_wfy4/racecar.jpg
cjy_wfy4/racestart.wav
cjy_wfy4/tiantiande.wav
cjy_wfy4/photos/1.jpg
cjy_wfy4/photos/10.jpg
cjy_wfy4/photos/11.jpg
cjy_wfy4/photos/12.jpg
cjy_wfy4/photos/13.jpg
cjy_wfy4/photos/14.jpg
cjy_wfy4/photos/15.jpg
cjy_wfy4/photos/2.jpg
cjy_wfy4/photos/3.jpg
cjy_wfy4/photos/4.jpg
cjy_wfy4/photos/5.jpg
cjy_wfy4/photos/6.jpg
cjy_wfy4/photos/7.jpg
cjy_wfy4/photos/70.jpg
cjy_wfy4/photos/8.jpg
cjy_wfy4/photos/9.jpg
cjy_wfy4-0.0.1.dist-info/LICENSE
cjy_wfy4-0.0.1.dist-info/METADATA
cjy_wfy4-0.0.1.dist-info/WHEEL
cjy_wfy4-0.0.1.dist-info/top_level.txt
cjy_wfy4-0.0.1.dist-info/RECORD
